dvt_core-0.58.8.dist-info/RECORD
dvt_core-0.58.8.dist-info/WHEEL
dvt_core-0.58.8.dist-info/entry_points.txt
dvt_core-0.58.8.dist-info/top_level.txt
dvt_core-0.58.8.dist-info/METADATA
dbt/query_analyzer.cpython-312-darwin.so
dbt/hooks.py
dbt/version.py
dbt/_pydantic_shim.py
dbt/flags.py
dbt/constants.py
dbt/selected_resources.py
dbt/query_analyzer.py
dbt/__init__.py
dbt/links.py
dbt/env_vars.py
dbt/deprecations.py
dbt/compilation.py
dbt/py.typed
dbt/exceptions.py
dbt/node_types.py
dbt/mp_context.py
dbt/profiler.py
dbt/tracking.py
dbt/internal_deprecations.py
dbt/clients/git.py
dbt/clients/registry.py
dbt/clients/__init__.py
dbt/clients/jinja.py
dbt/clients/jinja_static.py
dbt/clients/yaml_helper.py
dbt/clients/checked_load.py
dbt/event_time/sample_window.py
dbt/event_time/event_time.py
dbt/artifacts/__init__.py
dbt/artifacts/resources/__init__.py
dbt/artifacts/resources/types.py
dbt/artifacts/resources/base.py
dbt/artifacts/resources/v1/catalog.py
dbt/artifacts/resources/v1/documentation.py
dbt/artifacts/resources/v1/config.py
dbt/artifacts/resources/v1/source_definition.py
dbt/artifacts/resources/v1/analysis.py
dbt/artifacts/resources/v1/semantic_layer_components.py
dbt/artifacts/resources/v1/unit_test_definition.py
dbt/artifacts/resources/v1/semantic_model.py
dbt/artifacts/resources/v1/exposure.py
dbt/artifacts/resources/v1/hook.py
dbt/artifacts/resources/v1/saved_query.py
dbt/artifacts/resources/v1/owner.py
dbt/artifacts/resources/v1/generic_test.py
dbt/artifacts/resources/v1/model.py
dbt/artifacts/resources/v1/metric.py
dbt/artifacts/resources/v1/sql_operation.py
dbt/artifacts/resources/v1/seed.py
dbt/artifacts/resources/v1/singular_test.py
dbt/artifacts/resources/v1/group.py
dbt/artifacts/resources/v1/components.py
dbt/artifacts/resources/v1/macro.py
dbt/artifacts/resources/v1/function.py
dbt/artifacts/resources/v1/snapshot.py
dbt/artifacts/utils/validation.py
dbt/artifacts/exceptions/__init__.py
dbt/artifacts/exceptions/schemas.py
dbt/artifacts/schemas/results.py
dbt/artifacts/schemas/__init__.py
dbt/artifacts/schemas/batch_results.py
dbt/artifacts/schemas/base.py
