Metadata-Version: 2.4
Name: dvt-core
Version: 0.58.8
Summary: DVT (Data Virtualization Tool) - Multi-source data federation and transformation with Spark-unified compute layer.
Author: DVT Contributors
Maintainer: DVT Contributors
License-Expression: Apache-2.0
Project-URL: Homepage, https://github.com/dvt-core/dvt-core
Project-URL: Documentation, https://github.com/dvt-core/dvt-core#readme
Project-URL: Repository, https://github.com/dvt-core/dvt-core.git
Project-URL: Issues, https://github.com/dvt-core/dvt-core/issues
Keywords: data,virtualization,federation,multi-source,dbt,analytics,transform,spark,jdbc,databricks
Classifier: Development Status :: 4 - Beta
Classifier: Operating System :: MacOS :: MacOS X
Classifier: Operating System :: POSIX :: Linux
Classifier: Programming Language :: Python
Classifier: Programming Language :: Python :: 3.10
Classifier: Programming Language :: Python :: 3.11
Classifier: Programming Language :: Python :: 3.12
Classifier: Programming Language :: Python :: 3.13
Classifier: Programming Language :: Python :: Implementation :: CPython
Requires-Python: >=3.10
Requires-Dist: agate<1.10,>=1.7.0
Requires-Dist: Jinja2<4,>=3.1.3
Requires-Dist: mashumaro[msgpack]<3.15,>=3.9
Requires-Dist: click<9.0,>=8.0.2
Requires-Dist: jsonschema<5.0,>=4.19.1
Requires-Dist: networkx<4.0,>=2.3
Requires-Dist: protobuf<7.0,>=6.0
Requires-Dist: requests<3.0.0
Requires-Dist: snowplow-tracker<2.0,>=1.0.2
Requires-Dist: pathspec<0.13,>=0.9
Requires-Dist: sqlparse<0.6.0,>=0.5.0
Requires-Dist: dbt-extractor<=0.6,>=0.5.0
Requires-Dist: dbt-semantic-interfaces<0.10,>=0.9.0
Requires-Dist: dbt-common<2.0,>=1.27.0
Requires-Dist: dbt-adapters<2.0,>=1.15.5
Requires-Dist: dbt-protos<2.0,>=1.0.375
Requires-Dist: pydantic<3
Requires-Dist: packaging>20.9
Requires-Dist: pytz>=2015.7
Requires-Dist: pyyaml>=6.0
Requires-Dist: daff>=1.3.46
Requires-Dist: typing-extensions>=4.4
Requires-Dist: dbt-postgres<2.0,>=1.9.0
Requires-Dist: pyspark<5.0.0,>=3.5.0
Requires-Dist: duckdb>=0.9.0
Requires-Dist: rich>=13.0.0
Provides-Extra: databricks
Requires-Dist: databricks-connect>=13.0.0; extra == "databricks"
